shunollo-0.3.10.dist-info/licenses/LICENSE
shunollo_core/LICENSE
shunollo_core/__init__.py
shunollo_core/api.py
shunollo_core/config.py
shunollo_core/domain_adapter.py
shunollo_core/interfaces.py
shunollo_core/models.py
shunollo_core/physics_flow.py
shunollo_core/actions/__init__.py
shunollo_core/actions/motor_cortex.py
shunollo_core/agents/__init__.py
shunollo_core/agents/base_agent.py
shunollo_core/agents/prompt_builder.py
shunollo_core/brain/__init__.py
shunollo_core/brain/autoencoder.py
shunollo_core/brain/neural_net.py
shunollo_core/cognition/active_inference.py
shunollo_core/cognition/brocas_area.py
shunollo_core/cognition/decision.py
shunollo_core/cognition/wernickes_area.py
shunollo_core/configs/signature_rules.yml
shunollo_core/connectors/base_connector.py
shunollo_core/data/codon_memory.json
shunollo_core/data/experiments/test_01_reflex.pcap
shunollo_core/data/experiments/test_02_rhythm.pcap
shunollo_core/data/experiments/test_03_texture.pcap
shunollo_core/data/experiments/test_04_vigilance.pcap
shunollo_core/data/experiments/test_05_overload.pcap
shunollo_core/feedback/__init__.py
shunollo_core/feedback/agent_feedback.jsonl
shunollo_core/feedback/agent_feedback.py
shunollo_core/feedback/audit_log.py
shunollo_core/feedback/feedback_store.py
shunollo_core/feedback/feedback_tracker.py
shunollo_core/feedback/score_utils.py
shunollo_core/feedback/scoring.py
shunollo_core/feedback/training_loop.py
shunollo_core/governance/training_governor.py
shunollo_core/learning/synaptic_plasticity.py
shunollo_core/memory/__init__.py
shunollo_core/memory/base.py
shunollo_core/memory/hippocampus.py
shunollo_core/memory/holographic.py
shunollo_core/motor/motor_cortex.py
shunollo_core/perception/agent_perception.py
shunollo_core/perception/auditory_cortex.py
shunollo_core/perception/codon_builder.py
shunollo_core/perception/codon_memory.py
shunollo_core/perception/confidence.py
shunollo_core/perception/generic_transducer.py
shunollo_core/perception/glossary.py
shunollo_core/perception/gustatory_cortex.py
shunollo-0.3.10.dist-info/METADATA
shunollo-0.3.10.dist-info/WHEEL
shunollo-0.3.10.dist-info/top_level.txt
shunollo-0.3.10.dist-info/RECORD
