Metadata-Version: 2.4
Name: shunollo
Version: 0.3.10
Summary: Biomimetic Physics Engine for Cognitive Architectures
Author-email: Austin <austin@shunollo.org>
License: Apache-2.0
Project-URL: Homepage, https://github.com/TheLazyEyedJedi/Shunollo
Project-URL: Bug Tracker, https://github.com/TheLazyEyedJedi/Shunollo/issues
Project-URL: Documentation, https://github.com/TheLazyEyedJedi/Shunollo#readme
Classifier: Programming Language :: Python :: 3
Classifier: License :: OSI Approved :: Apache Software License
Classifier: Operating System :: OS Independent
Classifier: Topic :: Scientific/Engineering :: Physics
Classifier: Topic :: Scientific/Engineering :: Artificial Intelligence
Requires-Python: >=3.9
License-File: LICENSE
Requires-Dist: numpy>=1.20.0
Requires-Dist: scipy>=1.7.0
Requires-Dist: fastapi>=0.68.0
Requires-Dist: uvicorn>=0.15.0
Requires-Dist: sqlalchemy>=1.4.0
Requires-Dist: pydantic>=1.8.0
Requires-Dist: pillow>=8.0.0
Requires-Dist: pyyaml>=5.0
Provides-Extra: runtime
Requires-Dist: redis>=4.0.0; extra == "runtime"
Provides-Extra: dev
Requires-Dist: pytest>=7.0.0; extra == "dev"
Requires-Dist: black; extra == "dev"
Requires-Dist: ruff; extra == "dev"
Dynamic: license-file
